deployv_addon_gitlab_tools/__init__.py
deployv_addon_gitlab_tools/checkers.py
deployv_addon_gitlab_tools/common.py
deployv_addon_gitlab_tools/get_addons.py
deployv_addon_gitlab_tools/commands/__init__.py
deployv_addon_gitlab_tools/commands/build_image.py
deployv_addon_gitlab_tools/commands/check_keys.py
deployv_addon_gitlab_tools/commands/check_log.py
deployv_addon_gitlab_tools/commands/deployv_tests.py
deployv_addon_gitlab_tools/commands/push_coverage.py
deployv_addon_gitlab_tools/commands/test_image.py
deployv_addon_gitlab_tools/commands/test_images.py
deployv_addon_gitlab_tools/commands/test_repo.py
deployv_addon_gitlab_tools/commands/upload_image.py
deployv_addon_gitlab_tools-0.2.45.dist-info/AUTHORS.rst
deployv_addon_gitlab_tools-0.2.45.dist-info/LICENSE
deployv_addon_gitlab_tools-0.2.45.dist-info/METADATA
deployv_addon_gitlab_tools-0.2.45.dist-info/WHEEL
deployv_addon_gitlab_tools-0.2.45.dist-info/entry_points.txt
deployv_addon_gitlab_tools-0.2.45.dist-info/top_level.txt
deployv_addon_gitlab_tools-0.2.45.dist-info/RECORD
