Metadata-Version: 2.1
Name: deployv-addon-gitlab-tools
Version: 0.2.45
Summary: Deployv addon: Gitlab tools. Generated by cookiecutter and cookiecutter-deploy-addon.
Home-page: https://github.com/Vauxoo/deployv-addon-gitlab-tools
Author: Vauxoo
Author-email: info@vauxoo.com
License: BSD
Classifier: Development Status :: 5 - Production/Stable
Classifier: Intended Audience :: Developers
Classifier: License :: OSI Approved :: BSD License
Classifier: Operating System :: Unix
Classifier: Operating System :: POSIX
Classifier: Operating System :: Microsoft :: Windows
Classifier: Programming Language :: Python
Classifier: Programming Language :: Python :: 2.7
Classifier: Programming Language :: Python :: 3
Classifier: Programming Language :: Python :: 3.3
Classifier: Programming Language :: Python :: 3.4
Classifier: Programming Language :: Python :: 3.5
Classifier: Programming Language :: Python :: Implementation :: CPython
Classifier: Programming Language :: Python :: Implementation :: PyPy
Classifier: Topic :: Utilities
License-File: LICENSE
License-File: AUTHORS.rst
Requires-Dist: deployv
Requires-Dist: future
